{
  "company": {
    "name": "마이다스",
    "industry": "IT/소프트웨어",
    "company_size": "mid-size",
    "location": "서울",
    "website": null
  },
  "job_posting": {
    "title": "백엔드 개발 (신입/경력)",
    "description": "안정적이고 확장 가능한 백엔드 시스템 구축",
    "raw_text": "백엔드 개발 (신입/경력)\n마이다스에서 개발하는 서비스를 설계·구축·운영하며 안정적이고 확장 가능한 시스템을 만드는 역할입니다.\n\nAPI 설계부터 대규모 데이터 처리, CI/CD 운영까지 전 과정을 경험하며 백엔드 전문가로 성장할 수 있습니다.\n\n합류하게 되면 이런 일을 하게 돼요\n\n- Java / Spring Boot / Kotlin 기반 백엔드 서비스를 개발·운영해요.\n- RESTful API, WebSocket 기반 서비스를 설계·구현해요.\n- 대규모 데이터 처리를 위한 DB 구조를 설계하고 최적화해요.\n- CI/CD 파이프라인을 구축하고 클라우드 환경에서 서비스를 운영해요.\n- 테스트 코드 작성, 코드 품질 관리 및 성능 최적화를 수행해요.\n- 애자일 팀과 협업하며 코드 리뷰 및 지속적 개선을 실천해요.\n\n이런 분과 함께 일하고 싶어요\n\n- Java / Kotlin / Spring Framework를 활용한 백엔드 개발 경험이 있는 분\n- RDBMS 설계 및 최적화 경험이 있는 분\n- RESTful API 설계 및 구현 역량을 갖춘 분\n- Git 등 협업 툴과 CI/CD 환경 경험이 있는 분\n\n이런 분을 우대해요!\n\n- 메시지 큐(Kafka, RabbitMQ 등) 및 이벤트 드리븐 아키텍처 경험이 있는 분\n- 대규모 트래픽 서비스 운영 경험이 있는 분\n- TDD 및 테스트 자동화 경험이 있는 분\n- 클라우드(AWS, GCP, Azure) 기반 서비스 운영 경험이 있는 분\n- AI/ML, 데이터 처리 및 성능 최적화 경험이 있는 분\n\n이런 태도와 역량을 기대해요\n\n- 단순 기능 구현을 넘어 제품·사용자 가치를 고려하는 사고\n- 문제를 끈기 있게 파고들고 개선 방향을 주도적으로 제안하는 태도\n- 단순히 맡은 기능만 구현하는 것이 아닌 기획·디자인·운영 관점까지 고려해 제품 가치를 높이려는 태도\n- 서비스 목표를 고려해 우선순위를 정하고 문제 해결 방향을 제안할 수 있는 사고력\n- 코드와 제품의 퀄리티를 위해 끊임없이 개선하려는 태도\n- 새로운 기술을 탐색하고 학습하는 데 두려움이 없는 학습 민첩성\n\n함께하기 위한 여정이에요\n\n지원하기 > 역량검사, 개발 구현 능력 검사 > 커피챗 > 최종 합격",
    "requirements": {
      "required": [
        "Java / Kotlin / Spring Framework를 활용한 백엔드 개발 경험",
        "RDBMS 설계 및 최적화 경험",
        "RESTful API 설계 및 구현 역량",
        "Git 등 협업 툴과 CI/CD 환경 경험"
      ],
      "preferred": [
        "메시지 큐(Kafka, RabbitMQ 등) 및 이벤트 드리븐 아키텍처 경험",
        "대규모 트래픽 서비스 운영 경험",
        "TDD 및 테스트 자동화 경험",
        "클라우드(AWS, GCP, Azure) 기반 서비스 운영 경험",
        "AI/ML, 데이터 처리 및 성능 최적화 경험"
      ]
    },
    "responsibilities": [
      "Java / Spring Boot / Kotlin 기반 백엔드 서비스를 개발·운영",
      "RESTful API, WebSocket 기반 서비스를 설계·구현",
      "대규모 데이터 처리를 위한 DB 구조를 설계하고 최적화",
      "CI/CD 파이프라인을 구축하고 클라우드 환경에서 서비스를 운영",
      "테스트 코드 작성, 코드 품질 관리 및 성능 최적화를 수행",
      "애자일 팀과 협업하며 코드 리뷰 및 지속적 개선을 실천"
    ],
    "qualifications": {
      "education": "학력무관",
      "experience": "신입/경력",
      "certifications": []
    },
    "benefits": [],
    "employment_type": "full-time",
    "experience_level": "junior",
    "min_experience_years": 0,
    "max_experience_years": null,
    "salary_min": null,
    "salary_max": null,
    "salary_currency": "KRW",
    "location": "서울",
    "remote_type": "onsite",
    "source": "midas",
    "external_url": null,
    "posted_at": "2024-01-01",
    "expires_at": null
  }
}
