{
  "company": {
    "name": "캐치테이블",
    "industry": "IT/인터넷",
    "company_size": "mid-size",
    "location": "경기 성남시 판교",
    "website": "https://catchtable.co.kr"
  },
  "job_posting": {
    "title": "BizOps Software Engineer (3년 차 이상)",
    "description": "사내 업무 시스템 개발 및 운영, 프로세스 자동화를 통한 업무 효율화",
    "raw_text": "BizOps Sofrware Engineer (3년 차 이상)\n\"즐거운 미식생활의 ​시작, ​캐치테이블\" \n\n ​누군가에는 설레는 ​약속이고, 또 다른 이에게는 ​중요한 ​비즈니스의 시작입니다.\n\n그 ​중요한 순간들이 더 ​즐겁고 간편해지도록, ​캐치테이블은 ​예약, 웨이팅, ​포스, ​픽업, ​결제까지 아우르는\n\n'역사상 최초의 ​요식업 ​슈퍼플랫폼'을 만들어 나가고 ​있습니다.\n\n\n\n\"국내 ​1위 ​레스토랑 예약 서비스\"\n실시간 ​웨이팅 시스템 ​'캐치테이블 ​웨이팅'\nB2C & ​B2B 올인원 ​통합 ​솔루션\n예약금 0원 '캐치페이', ​티맵 연동, ​AI 레스토랑 추천, 글로벌 예약 (일본)까지\n\n\n 앞으로 우리는 단일 기능의 서비스를 넘어\n\n요식업의 모든 접점을 하나로 통합하는 '슈퍼플랫폼'으로 요식업 산업의 새로운 기준을 만들어 나갈 것입니다.\n\n그 변화의 한가운데에서 함께할 동료를 기다립니다.\n\n\n\n\n[캐치테이블 합류 여정]\n\n서류 접수 > 직무 적합성 검사 > 1차 인터뷰 > 2차 인터뷰 > 레퍼런스 체크 > 처우 협의 > 최종 합격 및 입사\n\n※ 직무 적합성 검사는 채용의 참고 자료로만 활용되며, 합격 여부를 결정짓는 기준으로 사용되지 않습니다.\n\n\n\n[팀 소개]\n\nBusiness Operations 팀을 소개합니다.\n\nBizOps 팀은 캐치테이블의 비즈니스 운영을 기술과 데이터 기반으로 혁신하는 조직입니다.\n\n회사의 다양한 운영 프로세스를 깊이 이해하고, 이를 시스템화 · 자동화하여 구성원이 더 효율적으로 일할 수 있도록 돕는 것이 팀의 핵심 미션입니다.\n\n현재 팀은 Program Manager 로 구성되어 있으며, \n\n현업과의 긴밀한 협업을 통해 문제를 발굴하고 솔루션을 기획하는 역할을 담당합니다. \n\n앞으로 합류할 개발자와 함께 기획부터 설계, 구현까지 전 과정을 빠르게 실행하고 개선하며, 업무 효율화 플랫폼의 중심 엔지니어링 조직으로 성장해 나갈 예정입니다.\n\nBizOps 팀은 단순한 운영 지원 조직이 아니라,\n\n내부 시스템을 제품(Product)처럼 바라보고 설계하며,\n비즈니스 임팩트를 만드는 운영 혁신 프로젝트를 추진하고,\n효율화와 자동화로 운영의 한계를 넘어서는 팀을 지향합니다.\n\n\n[주요업무]\n\n사내 업무 시스템(예약, 결제, 인사, 근태, 전자결재 등) 개발 및 운영\n사내 프로세스 자동화 및 업무 효율화 도구 구축 (RPA, Workflow automation 등)\n다양한 SaaS 및 내부 시스템 간 API/데이터 연동\nBizOps 요구사항을 기반으로 한 대시보드/리포트 구축\n신규 사내 플랫폼/툴 도입 및 커스터마이징\n\n\n[자격요건]\n\n유관 경력 3년 이상 또는 그에 준하는 Full Stack 개발 경험을 보유하신 분\nBackend 개발 경험 : Spring Boot (Java/Kotlin), Node.js, Python 등 중 하나 이상 사용 경험\nFrontend 개발 경험 : React.js, Vue.js, TypeScript 등 프레임워크 활용 경험\nDatabase 활용 경험 : MySQL, PostgreSQL 등 관계형 DB 기반 개발 경험\nRESTful API 및 Webhook 기반 연동 개발 경험\n문제 해결 중심적 사고와 새로운 영역에 대한 빠른 학습 능력\n\n\n[기술스택]\n\n주요 기술 : React.js, TypeScript, Spring Boot, JPA, Redis, MySQL, K8S(eks)\n인프라 : AWS (EC2, RDS, S3, 등)\n업무 도구 : Git, Jira, Slack\n코드리뷰 : Github PR\n\n\n[우대사항]\n\nERP, 그룹웨어, CRM, Slack bot 등 사내 시스템 개발/운영 경험\nWorkflow automation 도구(Zapier, n8n, Airflow 등) 활용 경험\nBI 도구(Redash, QuickSight, Tableau, Looker 등) 사용 경험\n클라우드 환경(AWS, GCP) 경험\n새로운 플랫폼과 서비스, 툴을 탐구하는 데 즐거움을 느끼는 사람\n시스템 구조 이해력과 적응력이 높으신 분\n긍정적이고 밝은 에너지를 가진 분\n\n\n[기대하는 인재상]\n\n단순한 개발이 아니라 비즈니스 문제 해결에 초점을 맞추는 개발자\n다양한 부서와 협업하며 업무 효율을 극대화하는 솔루션을 만들 수 있는 사람\n자동화와 최적화에 흥미가 있고, 빠르게 실행하고 개선할 수 있는 사람\n원활하고 투명한 커뮤니케이션을 지향하는 사람\n꼼꼼하고 집요하게 문제를 해결하는 사람\n성장 의지와 자기 개발/계발을 즐기는 사람\n\n\n[혜택 및 복지]\n\n당신의 성장이 곧 캐치테이블의 성장\n- 독서모임을 위한 도서 및 직무 관련 도서, 세미나, 컨퍼런스 등 교육비 지원\n\n- 미식생활을 즐기는 자가 미식문화를 선도할 수 있음에 연간 캐치포인트 100만원 지원\n\n- 장기근속 포상 휴가 및 휴가비 지원 (3년: 5일, 100만원 / 5년, 7년: 10일, 300만원 / 10년: 20일, 500만원)\n\n\n\n일에만 집중할 수 있도록\n- 추가근무수당(1시간당 15,000원) 및 택시비(오후 11시 퇴근 경우) 지원\n\n- 점심 식사, 추가 근무의 경우 저녁 식사 지원\n\n- 다양한 음료와 간식, 커피 무제한 제공\n\n- 최고사양 IT 자산 지급\n\n- 넓은 오피스 및 편한 인프라 환경을 갖춘 판교 유스페이스 입주사\n\n- 선택적 근로시간제 운영(8~10시, 1시간 단위 출근시간 선택)\n\n- 정밀 건강 검진 2년에 1회 제공\n\n- 마음 건강 검진, 연간 4회 심리상담 지원\n\n- 복지를 편하게 이용하기 위한 개별 법인카드 지급\n\n\n\n소통&소통\n- 매월 랜덤으로 짝지어 점심 먹는 'Leaders Lunch Day'\n\n- 회사의 비전, 팀의 목표, 향후 계획 등을 CEO가 직접 공유하는 'Monthly Growth Meeting'\n\n- 개인의 성장에 집중하여 리더와 함께 이야기 나누는 'Monthly Feedback Meeting'\n\n- 신규 입사자 새로운 시작을 함께 도와주는 'Categorie'\n\n- 소통의 시너지를 위해 타 팀 구성원들과 함께하는 문화의 날 'Catch The Culture Day'\n\n\n\n기념일도 함께하는 캐치테이블\n- 생일 케이크, 생일 반차 및 상품권 지급\n\n- 명절(설날, 추석) 반차 및 상품권 지급\n\n\n\n\n[유의사항]\n\n제출 자료와 채용 프로세스 전반에서 허위사실 및 결격사유가 발견될 경우 채용이 취소될 수 있습니다.\n모든 공고는 수시채용으로, 합격자가 발생할 경우 조기 마감될 수 있습니다.\n채용 포지션에 따라 프로세스가 변경 또는 추가될 수 있습니다.",
    "requirements": {
      "required": [
        "유관 경력 3년 이상 또는 그에 준하는 Full Stack 개발 경험",
        "Backend 개발 경험 : Spring Boot (Java/Kotlin), Node.js, Python 등 중 하나 이상 사용 경험",
        "Frontend 개발 경험 : React.js, Vue.js, TypeScript 등 프레임워크 활용 경험",
        "Database 활용 경험 : MySQL, PostgreSQL 등 관계형 DB 기반 개발 경험",
        "RESTful API 및 Webhook 기반 연동 개발 경험",
        "문제 해결 중심적 사고와 새로운 영역에 대한 빠른 학습 능력"
      ],
      "preferred": [
        "ERP, 그룹웨어, CRM, Slack bot 등 사내 시스템 개발/운영 경험",
        "Workflow automation 도구(Zapier, n8n, Airflow 등) 활용 경험",
        "BI 도구(Redash, QuickSight, Tableau, Looker 등) 사용 경험",
        "클라우드 환경(AWS, GCP) 경험",
        "새로운 플랫폼과 서비스, 툴을 탐구하는 데 즐거움을 느끼는 사람",
        "시스템 구조 이해력과 적응력이 높으신 분",
        "긍정적이고 밝은 에너지를 가진 분"
      ]
    },
    "responsibilities": [
      "사내 업무 시스템(예약, 결제, 인사, 근태, 전자결재 등) 개발 및 운영",
      "사내 프로세스 자동화 및 업무 효율화 도구 구축 (RPA, Workflow automation 등)",
      "다양한 SaaS 및 내부 시스템 간 API/데이터 연동",
      "BizOps 요구사항을 기반으로 한 대시보드/리포트 구축",
      "신규 사내 플랫폼/툴 도입 및 커스터마이징"
    ],
    "qualifications": {
      "education": "학력무관",
      "experience": "경력 3년 이상",
      "certifications": []
    },
    "benefits": [
      "독서모임을 위한 도서 및 직무 관련 도서, 세미나, 컨퍼런스 등 교육비 지원",
      "연간 캐치포인트 100만원 지원",
      "장기근속 포상 휴가 및 휴가비 지원",
      "추가근무수당(1시간당 15,000원) 및 택시비 지원",
      "점심 식사, 추가 근무의 경우 저녁 식사 지원",
      "다양한 음료와 간식, 커피 무제한 제공",
      "최고사양 IT 자산 지급",
      "선택적 근로시간제 운영(8~10시, 1시간 단위 출근시간 선택)",
      "정밀 건강 검진 2년에 1회 제공",
      "마음 건강 검진, 연간 4회 심리상담 지원",
      "개별 법인카드 지급"
    ],
    "employment_type": "full-time",
    "experience_level": "mid",
    "min_experience_years": 3,
    "max_experience_years": null,
    "salary_min": null,
    "salary_max": null,
    "salary_currency": "KRW",
    "location": "경기 성남시 판교",
    "remote_type": "onsite",
    "source": "catchtable",
    "external_url": null,
    "posted_at": "2024-01-01",
    "expires_at": null
  }
}
